xdcheckin_ffmpeg/__init__.py
xdcheckin_ffmpeg/bin/__init__.py
xdcheckin_ffmpeg/bin/ffmpeg
xdcheckin_ffmpeg-1.0.9.dist-info/licenses/LICENSE
xdcheckin_ffmpeg-1.0.9.dist-info/licenses/LICENSE_ZIMBATM
xdcheckin_ffmpeg-1.0.9.dist-info/METADATA
xdcheckin_ffmpeg-1.0.9.dist-info/WHEEL
xdcheckin_ffmpeg-1.0.9.dist-info/top_level.txt
xdcheckin_ffmpeg-1.0.9.dist-info/RECORD
