Metadata-Version: 2.4
Name: Xdcheckin-FFmpeg
Version: 1.0.9
Summary: Minimal static FFmpeg with h.264 for Xdcheckin.
Author-email: Pairman <pairmanxlr@gmail.com>
License: BSD-2-Clause
Project-URL: Homepage, https://github.com/Pairman/Xdcheckin-FFmpeg
Project-URL: Changelog, https://github.com/Pairman/Xdcheckin-FFmpeg/blob/main/CHANGELOG.md
Keywords: xdcheckin,video,livestream,ffmpeg
Classifier: Programming Language :: Python :: 3
Classifier: License :: OSI Approved :: BSD License
Requires-Python: >=3.5
License-File: LICENSE
License-File: LICENSE_ZIMBATM
Dynamic: license-file
